{
  "main": {
    "name": "Dallin Romney",
    "first_name": "Dallin",
    "occupation": "Manufacturing Engineer, Software Developer",
    "description": "DESCRIPTION",
    "image": "profilepic.jpg",
    "bio": "Hi, I'm Dallin, welcome to my online portfolio. I enjoy creating, exploring, and connecting. Career experience is in manufacturing engineering and sales, but passion has shifted towards software development, especially web3. Offline you'll spot me with a book, a guitar, or a tennis racquet.",
    "email": "dallinromney@gmail.com",
    "address": {
      "city": "Salt Lake City, UT"
    },
    "socials": [
      {
        "name": "github",
        "url": "https://github.com/RomneyDa",
        "className": "fa fa-github"
      },
      {
        "name": "linkedin",
        "url": "https://www.linkedin.com/in/romneyda/",
        "className": "fa fa-linkedin"
      }
    ]
  },
  "resume": {
    "resumedownload": "https://s3.us-west-1.amazonaws.com/dallinromney.com/Dallin+Romney+Software+Engineer+Resume+2022-04-15.pdf",
    "resumelinks": [
      {
        "text": "Software Resume",
        "link": "https://s3.us-west-1.amazonaws.com/dallinromney.com/Dallin+Romney+Sales+Resume+2022-02-19.pdf"
      },
      {
        "text": "Sales Resume",
        "link": "https://s3.us-west-1.amazonaws.com/dallinromney.com/Dallin+Romney+Sales+Resume+2022-02-19.pdf"
      },
      {
        "text": "Engineering Resume",
        "link": "https://s3.us-west-1.amazonaws.com/dallinromney.com/Dallin+Romney+Sales+Resume+2022-02-19.pdf"
      }
    ],
    "skillmessage": "Confidence/proficiency",
    "education": [
      {
        "school": "University of Utah",
        "degree": "BS, Mechanical Engineering",
        "graduated": "May 2020",
        "description": "Design & Manufacturing emphasis. 3.83 GPA."
      },
      {
        "school": "College of Southern Idaho",
        "degree": "AA, Liberal Arts",
        "graduated": "August 2016",
        "description": "Summa cum laude, 4.0 GPA"
      }
    ],
    "work": [
      {
        "company": "Merit Medical Systems",
        "title": "Manufacturing Engineer",
        "years": "July 2020 - Present",
        "description": "Oversee daily operations for medical device manufacturing lines. Execute and manage interdisciplinary projects involving design, equipment/fixture, location, software, regulatory, accounting, material sourcing, specification, process, documentation, and other changes to reduce waste/costs and improve/optimize throughput, efficiency, safety, quality, and customer experience."
      },
      {
        "company": "Southwestern Advantage",
        "title": "Sales Manager and Salesman",
        "years": "March 2017 - August 2019",
        "description": "Executed all ordering, inventory, sales, accounting, social media, scheduling, and delivery in  personal educational products sales business. 3,000+ hours of direct door-to-door sales experience. 13,000+ prospect calls and thousands of full sales cycles. Personal sales growth of $12,400 -> $34,600 -> $44,600. Attended 100+ hours of advanced sales and leadership training. Coached ethical selling techniques and motivated/led salespeople in the field. Immersive experience with a focus on success principles like goal setting, schedule, and attitude/emotional management. Relocated to Pennsylvania and Alabama for 3 summers."
      },
      {
        "company": "University of Utah",
        "title": "Researcher",
        "years": "January 2018 - April 2019",
        "description": "Designed, simulated, and optimized hardware solutions for nanoscale near-field radiative heat transfer research, primarily using SolidWorks. Awarded the Dee Foundation Scholar Designation for excellence in local and environmental research."
      },
      {
        "company": "Self-employed",
        "title": "Tutor",
        "years": "Aug 2015 - Present",
        "description": "Tutor students in a wide range of courses, from entry-level to upper-division college courses. Mostly mathematics and engineering courses, but also basic music, English, reading, etc."
      }
    ],
    "skills": [
      {
        "name": "Direct Sales",
        "level": "98%"
      }, 
      {
        "name": "VBA (and MS Office)",
        "level": "95%"
      },
      {
        "name": "SolidWorks",
        "level": "90%"
      },
      {
        "name": "3D Modeling/Prototyping",
        "level": "90%"
      },
      {
        "name": "Eng Project Management",
        "level": "82%"
      }, 
      {
        "name": "Arduino C++",
        "level": "80%"
      },  
      {
        "name": "HTML/CSS",
        "level": "80%"
      },
      {
        "name": "Sales Management",
        "level": "78%"
      }, 
      {
        "name": "MATLAB",
        "level": "78%"
      },  
      
      {
        "name": "Javascript",
        "level": "75%"
      },
      {
        "name": "C#",
        "level": "70%"
      },
      {
        "name": "ReactJS",
        "level": "65%"
      },
      {
        "name": "Python",
        "level": "60%"
      },   
      {
        "name": "Learning :)",
        "level": "100%"
      }
    ],


    "other_skills": "Other skills I'm familiar with but would rate myself below 50% in include git, R, SQL, AWS, social media management, and React Native"
  },
  "portfolio": {
    "projects": [
      {
        "title": "Where Can I Pee?",
        "category": "React JS",
        "image": "wherecanipee.png",
        "url": "https://www.wherecanipee.art"
      },
      {
        "title": "Focus on Food Storage",
        "category": "HTML/CSS/JS, Stripe Payments",
        "image": "focusonfoodstorage.png",
        "url": "https://www.focusonfoodstorage.org"
      },
      {
        "title": "Foodcrew",
        "category": "React, Mobile-first, Netlify",
        "image": "foodcrew.png",
        "url": "https://jolly-ramanujan-5e1e4e.netlify.app/"
      },
      {
        "title": "Github User Search",
        "category": "React, Github API",
        "image": "githubusersearch.png",
        "url": "https://drgithubfinder.netlify.app/"
      }
    ]
  }

}
